LICENSE
MANIFEST.in
README.rst
setup.cfg
setup.py
django_erp_framework.egg-info/PKG-INFO
django_erp_framework.egg-info/SOURCES.txt
django_erp_framework.egg-info/dependency_links.txt
django_erp_framework.egg-info/requires.txt
django_erp_framework.egg-info/top_level.txt
erp_framework/__init__.py
erp_framework/apps.py
erp_framework/checks.py
erp_framework/doc_types.py
erp_framework/sites.py
erp_framework/activity/__init__.py
erp_framework/activity/admin.py
erp_framework/activity/apps.py
erp_framework/activity/models.py
erp_framework/activity/migrations/0001_initial.py
erp_framework/activity/migrations/0002_auto_20200711_1253.py
erp_framework/activity/migrations/0003_alter_myactivity_options.py
erp_framework/activity/migrations/__init__.py
erp_framework/admin/__init__.py
erp_framework/admin/admin.py
erp_framework/admin/apps.py
erp_framework/admin/base.py
erp_framework/admin/helpers.py
erp_framework/admin/jazzmin_integration/__init__.py
erp_framework/admin/jazzmin_integration/apps.py
erp_framework/base/__init__.py
erp_framework/base/app_settings.py
erp_framework/base/helpers.py
erp_framework/base/models.py
erp_framework/contrib/__init__.py
erp_framework/reporting/__init__.py
erp_framework/reporting/admin.py
erp_framework/reporting/apps.py
erp_framework/reporting/forms.py
erp_framework/reporting/models.py
erp_framework/reporting/printing.py
erp_framework/reporting/registry.py
erp_framework/reporting/views.py
erp_framework/reporting/migrations/0001_initial.py
erp_framework/reporting/migrations/__init__.py
erp_framework/reporting/templatetags/__init__.py
erp_framework/reporting/templatetags/erp_reporting_tags.py